upswingutil/__init__.py
upswingutil/global_variables.py
upswingutil/channel/__init__.py
upswingutil/channel/email.py
upswingutil/channel/notification.py
upswingutil/channel/whatsapp.py
upswingutil/db/__init__.py
upswingutil/db/firestoredb.py
upswingutil/db/mongodb.py
upswingutil/db/mongodb_mongoengine.py
upswingutil/db/model/__init__.py
upswingutil/db/model/guest.py
upswingutil/db/model/property.py
upswingutil/db/model/reservation.py
upswingutil/doorlock/__init__.py
upswingutil/doorlock/doorlock.py
upswingutil/grms/__init__.py
upswingutil/grms/grms.py
upswingutil/integrations/__init__.py
upswingutil/integrations/models/__init__.py
upswingutil/integrations/models/integrations.py
upswingutil/pms/__init__.py
upswingutil/pms/alvie.py
upswingutil/pms/oracle/__init__.py
upswingutil/pms/oracle/auth.py
upswingutil/pms/oracle/check_in.py
upswingutil/pms/oracle/reservation.py
upswingutil/pms/oracle/reservation_v2.py
upswingutil/pms/oracle/variables.py
upswingutil/pms/oracle_opera/__init__.py
upswingutil/pms/oracle_opera/check_in.py
upswingutil/pms/rms/__init__.py
upswingutil/pms/rms/auth.py
upswingutil/pms/rms/check_in.py
upswingutil/pms/rms/countries.py
upswingutil/pms/rms/reservation.py
upswingutil/pms/rms/reservation_v2.py
upswingutil/pms/rms/variables.py
upswingutil/resource/__init__.py
upswingutil/resource/cloud.py
upswingutil/resource/crypto.py
upswingutil/resource/firebase.py
upswingutil/resource/http_retry.py
upswingutil/resource/jwt.py
upswingutil/resource/logger.py
upswingutil/resource/qr_codes.py
upswingutil/resource/secret_manager.py
upswingutil/resource/user_management.py
upswingutil/schema/__init__.py
upswingutil/schema/alvie.py
upswingutil/schema/auth.py
upswingutil/schema/checkin.py
upswingutil/schema/country.py
upswingutil/schema/http.py
upswingutil/schema/organization_cfg.py
upswingutil/schema/property.py
upswingutil/schema/pubSub.py
upswingutil/schema/qr_codes.py
upswingutil/schema/reservation.py
upswingutil/schema/user_management.py
upswingutil-2.6.1.dist-info/METADATA
upswingutil-2.6.1.dist-info/WHEEL
upswingutil-2.6.1.dist-info/top_level.txt
upswingutil-2.6.1.dist-info/RECORD
