Metadata-Version: 2.1
Name: upswingutil
Version: 2.6.1
Summary: Utility package
Author: Harsh Mathur
Author-email: hmathur@upswing.cloud
Keywords: python,upswing
Classifier: Development Status :: 5 - Production/Stable
Classifier: Intended Audience :: Developers
Classifier: Programming Language :: Python :: 3
Classifier: Operating System :: MacOS :: MacOS X
Classifier: Operating System :: POSIX :: Linux
Classifier: Operating System :: Microsoft :: Windows
Requires-Dist: requests
Requires-Dist: pydantic
Requires-Dist: gcsfs
Requires-Dist: cryptography
Requires-Dist: fastapi
Requires-Dist: firebase-admin
Requires-Dist: pymongo
Requires-Dist: loguru
Requires-Dist: mongoengine
Requires-Dist: pycountry-convert
Requires-Dist: google-cloud-secret-manager (==2.0.0)
Requires-Dist: google-api-python-client
